{
  "deployments": {
    "vapi-call-handler": {
      "workflowId": "1IX82-PqM5HiZq7sUSfpf",
      "sourceFile": "n8n-workflow-vapi-call-handler.json",
      "lastDeployed": "2026-02-10T02:05:06.277Z",
      "name": "Equity Insurance - VAPI AI Receptionist (Main)",
      "nodeCount": 13,
      "active": true
    },
    "notifications-escalation": {
      "workflowId": "5LCW3l7WBBOClWIV",
      "sourceFile": "n8n-workflow-notifications.json",
      "lastDeployed": "2026-03-03T00:32:00.000Z",
      "name": "Equity Insurance - Post-Call Notifications & Escalation",
      "nodeCount": 13,
      "active": false,
      "note": "Added 4 SMS nodes (AWS SNS). Needs SMTP credentials for email activation. AWS credential ID: k7djkf7WKIHVtcRl"
    }
  }
}
